Metadata-Version: 1.0
Name: aksoso
Version: 0.1.8
Summary: transform python file to .so file
Home-page: https://github.com/AustinKuture/AKso.git
Author: Kuture
Author-email: kuture@163.com
License: MIT Licence
Keywords: pip,aksoso,.so,cython,kuture,transform so
Platform: any
